fdsauth/Apisix.py
fdsauth/Consumer.py
fdsauth/Keycloak.py
fdsauth/__init__.py
fdsauth/credentials_utils.py
fdsauth/http_client.py
fdsauth-0.0.6.dist-info/METADATA
fdsauth-0.0.6.dist-info/WHEEL
fdsauth-0.0.6.dist-info/top_level.txt
fdsauth-0.0.6.dist-info/RECORD
