Metadata-Version: 2.2
Name: fdsauth
Version: 0.0.6
Summary: Python authentication for FIWARE Data Space
Home-page: https://github.com/CitCom-VRAIN/fdsauth
Author: Joan Ciprià
Author-email: joamoteo@upv.es
Requires-Dist: requests
Requires-Dist: tenacity
Requires-Dist: jwt
Dynamic: author
Dynamic: author-email
Dynamic: description
Dynamic: description-content-type
Dynamic: home-page
Dynamic: requires-dist
Dynamic: summary
